Metadata-Version: 1.0
Name: standard-stats-distributions
Version: 0.1
Summary: Gaussian and Binomial distributions
Home-page: UNKNOWN
Author: Mickey Sompong
Author-email: UNKNOWN
License: UNKNOWN
Platform: UNKNOWN
